displacement/__init__.py
displacement-0.0.1.dist-info/LICENSE.txt
displacement-0.0.1.dist-info/METADATA
displacement-0.0.1.dist-info/WHEEL
displacement-0.0.1.dist-info/top_level.txt
displacement-0.0.1.dist-info/RECORD
